{
  "objectInfo" : {
    "id" : "80NvlahuJgvkN0RsmiEgk9",
    "name" : "BS-IICS-Login",
    "type" : "BSERVICE",
    "metadata" : {
      "modelVersion" : {
        "major" : 0,
        "minor" : 0
      },
      "repoInfo" : {
        "repoHandle" : "01CWNJ27000000000002"
      },
      "contextAttributes" : [ {
        "name" : "id",
        "value" : "@1"
      }, {
        "name" : "01CWNJ28000000000002",
        "value" : "80NvlahuJgvkN0RsmiEgk9@getUserLoginDetails"
      } ],
      "additionalInfo" : {
        "description" : "",
        "contentType" : "JSON",
        "documentState" : "VALID"
      }
    }
  },
  "dataFileExtension" : "zip",
  "updateTime" : "2024-11-18T06:09:13.088Z",
  "objectRefs" : [ {
    "id" : "2OmgnRO1SanjsnvsjoR7ec",
    "name" : "conn-IICS-User-Login",
    "type" : "Connection",
    "metadata" : {
      "modelVersion" : {
        "major" : 0,
        "minor" : 0
      },
      "repoInfo" : {
        "repoHandle" : "01CWNJ0B000000000019"
      },
      "contextAttributes" : null,
      "additionalInfo" : {
        "description" : null,
        "contentType" : "JSON",
        "documentState" : "COMPLETE"
      }
    },
    "path" : "/SYS"
  } ],
  "readableFileExtension" : null,
  "readableFilePresent" : false
}